{
  "file": "17t",
  "num_speakers": 1,
  "speakers": [
    "SPEAKER_01"
  ],
  "segments": [
    {
      "speaker": "SPEAKER_01",
      "text": "ইয়াহিয়া আমিন: আমরা যদি আসলে একটা সুস্থ স্কিনের একটা যদি রুটিন খুঁজি একটা সুস্থ স্কিন কেয়ারের রুটিন আসলে কেমন হওয়া উচিত ফর এভিওয়ান অথবা রেগুলার একটা ছেলে মেয়ের জন্য \n\n\n\nডা. সুষমা রেজা: আচ্ছা এটাকে আমরা একটা রুলস হিসেবে সেট করি সবসময় সেটাকে আমরা থ্রি টু ওয়ান বলি থ্রি টু ওয়ান মানে থ্রি আমি অলরেডি আপনাকে একদম শুরুর দিকে বলেছি থ্রি মানে বেসিক তিনটা আইটেম হ্যা একটা ফেস ওয়াশ ময়েশ্চারাইজার সান ব্লক থ্রি শেষ এখন আসেন টু আপনি যাবেন কি যাবেন না এটা আপনি যদি নিজে বোঝেন সিদ্ধান্ত নেবেন অথবা একজন ডার্মাটোলজি দেখিয়ে নিবেন টু বলতে আমরা অনেকগুলো জিনিসকে বুঝতে পারি টু বলতে প্রথমে বুঝাই হলো মর্নিং এট নাইট দুই বেলা টু এর একটা ব্যাখ্যা হতে পারে যেঅক্টিভ গুলোর কথা আমরা বলেছি নামাইড আলফার বিটেন ভিটামিন সি অজেলিক এসিড নিড বেস টার্গেটেড যে সেরামগুলো আমাদের বিভিন্ন প্রবলেম সারাতে লাগে টু এর ব্যাখ্যাটা এরকম হতে পারে যে সকালে একটা আমি একটিভ ইনগ্রিডিয়েন্ট রাখছি রাতে একটা রাখছি"
    }
  ],
  "full_text": "ইয়াহিয়া আমিন: আমরা যদি আসলে একটা সুস্থ স্কিনের একটা যদি রুটিন খুঁজি একটা সুস্থ স্কিন কেয়ারের রুটিন আসলে কেমন হওয়া উচিত ফর এভিওয়ান অথবা রেগুলার একটা ছেলে মেয়ের জন্য \n\n\n\nডা. সুষমা রেজা: আচ্ছা এটাকে আমরা একটা রুলস হিসেবে সেট করি সবসময় সেটাকে আমরা থ্রি টু ওয়ান বলি থ্রি টু ওয়ান মানে থ্রি আমি অলরেডি আপনাকে একদম শুরুর দিকে বলেছি থ্রি মানে বেসিক তিনটা আইটেম হ্যা একটা ফেস ওয়াশ ময়েশ্চারাইজার সান ব্লক থ্রি শেষ এখন আসেন টু আপনি যাবেন কি যাবেন না এটা আপনি যদি নিজে বোঝেন সিদ্ধান্ত নেবেন অথবা একজন ডার্মাটোলজি দেখিয়ে নিবেন টু বলতে আমরা অনেকগুলো জিনিসকে বুঝতে পারি টু বলতে প্রথমে বুঝাই হলো মর্নিং এট নাইট দুই বেলা টু এর একটা ব্যাখ্যা হতে পারে যেঅক্টিভ গুলোর কথা আমরা বলেছি নামাইড আলফার বিটেন ভিটামিন সি অজেলিক এসিড নিড বেস টার্গেটেড যে সেরামগুলো আমাদের বিভিন্ন প্রবলেম সারাতে লাগে টু এর ব্যাখ্যাটা এরকম হতে পারে যে সকালে একটা আমি একটিভ ইনগ্রিডিয়েন্ট রাখছি রাতে একটা রাখছি"
}