{
  "file": "22t",
  "num_speakers": 1,
  "speakers": [
    "SPEAKER_01"
  ],
  "segments": [
    {
      "speaker": "SPEAKER_01",
      "text": "ইয়াহিয়া মো. আমিন: আমাদের লোকাল জায়েন্টদের আরএনডি ডিপার্টমেন্ট নাই সো তারাও কাজ করতে চায় হচ্ছে গিয়ে এভারেজ লোকজনদেরকে নিয়ে সো ওই ইকোসিস্টেমের ডিমান্ড সাপ্লাই সাইকেলটা যেটা সুইডেনে আছে বা চায়নাতে আছে সেটা আমরা তৈরি করতে পারি নাই। কারণ উই আর উই আর কমফর্টেবল উইথ আইডিয়া আমার ট্যালেন্টেড ছেলে পেলে আমাদের দেশে থাকবে না দ্যাটস মাইন্ডসেট প্রবলেম\n\n\n\n\nড. ইমাদুর রহমান: আমি যেটা শুরুতেই বলেছিলাম যে নেক্সট 15 টু 20 ইয়ারস ইজ ভেরি ইম্পরটেন্ট এন্ড আই এম ভেরি হোপফুল আইম ভেরি হোপফুল ইউথ আর মাচ মোর এনার্জাইজ নাইউথ মাচ মোর ইনফরম এন্ড আমি ওদেরকে আইিম কারেন্ট ইয়াং জেনারেশন মোরন্স আওয়ার জেনারেশন \n\n\n\nইয়াহিয়া মো. আমিন: আমরা যদি মানে লাস্ট একটা ডাইমেনশনে কথা বলি একদিকে যেমন আপনি এরকসনের আপনি প্রিন্সিপাল সাইন্টিস্ট রিসার্চ আর ইন্ডিয়ান ডিপার্টমেন্টের হিসেবে কাজ করেছেন এবং তার আগেও খুব ভালো জায়গাগুলোতে ছিলেন। আবার আপনি মুসলিম উম্মাহ বা মুসলিম কমিউনিটির সাথে ইউ আর ভেরি ইনভলভড। সুইডেনে, লন্ডনে ইউ আর ভেরি ইনভলভ অল থ্রু আউট। সো ওইটাও আপনার এটলিস্ট ইয়ার্স প্লাস ধরে আপনি ভেরি ইনভল্ভ। আমি যদি একটু মুসলিমদের পৃথিবীতে অনেক কিছু হয়ে গেছে। আপনার এই লাইফ টাইমে।"
    }
  ],
  "full_text": "ইয়াহিয়া মো. আমিন: আমাদের লোকাল জায়েন্টদের আরএনডি ডিপার্টমেন্ট নাই সো তারাও কাজ করতে চায় হচ্ছে গিয়ে এভারেজ লোকজনদেরকে নিয়ে সো ওই ইকোসিস্টেমের ডিমান্ড সাপ্লাই সাইকেলটা যেটা সুইডেনে আছে বা চায়নাতে আছে সেটা আমরা তৈরি করতে পারি নাই। কারণ উই আর উই আর কমফর্টেবল উইথ আইডিয়া আমার ট্যালেন্টেড ছেলে পেলে আমাদের দেশে থাকবে না দ্যাটস মাইন্ডসেট প্রবলেম\n\n\n\n\nড. ইমাদুর রহমান: আমি যেটা শুরুতেই বলেছিলাম যে নেক্সট 15 টু 20 ইয়ারস ইজ ভেরি ইম্পরটেন্ট এন্ড আই এম ভেরি হোপফুল আইম ভেরি হোপফুল ইউথ আর মাচ মোর এনার্জাইজ নাইউথ মাচ মোর ইনফরম এন্ড আমি ওদেরকে আইিম কারেন্ট ইয়াং জেনারেশন মোরন্স আওয়ার জেনারেশন \n\n\n\nইয়াহিয়া মো. আমিন: আমরা যদি মানে লাস্ট একটা ডাইমেনশনে কথা বলি একদিকে যেমন আপনি এরকসনের আপনি প্রিন্সিপাল সাইন্টিস্ট রিসার্চ আর ইন্ডিয়ান ডিপার্টমেন্টের হিসেবে কাজ করেছেন এবং তার আগেও খুব ভালো জায়গাগুলোতে ছিলেন। আবার আপনি মুসলিম উম্মাহ বা মুসলিম কমিউনিটির সাথে ইউ আর ভেরি ইনভলভড। সুইডেনে, লন্ডনে ইউ আর ভেরি ইনভলভ অল থ্রু আউট। সো ওইটাও আপনার এটলিস্ট ইয়ার্স প্লাস ধরে আপনি ভেরি ইনভল্ভ। আমি যদি একটু মুসলিমদের পৃথিবীতে অনেক কিছু হয়ে গেছে। আপনার এই লাইফ টাইমে।"
}